chatGPT_automator/__init__.py
chatGPT_automator/master.py
chatGPT_automator-0.1.21.dist-info/LICENSE
chatGPT_automator-0.1.21.dist-info/METADATA
chatGPT_automator-0.1.21.dist-info/WHEEL
chatGPT_automator-0.1.21.dist-info/top_level.txt
chatGPT_automator-0.1.21.dist-info/RECORD
