Metadata-Version: 2.1
Name: chatGPT-automator
Version: 0.1.21
Summary: Regarding automating ChatGPT using Selenium in Python
Home-page: https://github.com/kevinljw/chatgpt_automator
Author: evinljw
Author-email: evin92@gmail.com
License: MIT
Classifier: Programming Language :: Python :: 3
Classifier: License :: OSI Approved :: MIT License
Classifier: Operating System :: OS Independent
Requires-Python: >=3.6
License-File: LICENSE
Requires-Dist: selenium >=3.14.1
Requires-Dist: webdriver-manager >=3.7.0
Requires-Dist: undetected-chromedriver >=3.5.4
